capsules/__init__.py
capsules/capsules.py
capsules-0.1.0.dist-info/LICENSE
capsules-0.1.0.dist-info/METADATA
capsules-0.1.0.dist-info/WHEEL
capsules-0.1.0.dist-info/top_level.txt
capsules-0.1.0.dist-info/RECORD
