Metadata-Version: 2.1
Name: capsules
Version: 0.1.0
Summary: Library for depositing a function definition inside a temporary module file.
Home-page: https://github.com/reity/capsules
Author: Andrei Lapets
Author-email: a@lapets.io
License: MIT
Platform: UNKNOWN
